{
  "id": "20220127-03",
  "date": "2022-01-27",
  "seq": 3,
  "title": "2022-01-27.03",
  "lines": [
    "we do know the time",
    "of birth through life also death",
    "when to embrace love"
  ],
  "tags": [
    "also",
    "birth",
    "death",
    "do",
    "embrace",
    "know",
    "life",
    "love",
    "of",
    "through",
    "time",
    "to",
    "when"
  ],
  "path_html": "data/2022/01/27/haiku.2022-01-27.03.html",
  "path_json": "data/2022/01/27/haiku.2022-01-27.03.json",
  "created": "2025-09-29T08:35:11.710711+00:00"
}