{
  "id": "20231205-05",
  "date": "2023-12-05",
  "seq": 5,
  "title": "2023-12-05.05",
  "lines": [
    "pale warm breaks slides",
    "ridge breaks passes mist footprint",
    "snow wind soft early"
  ],
  "tags": [
    "breaks",
    "footprint",
    "mist",
    "pale",
    "passes",
    "ridge",
    "slides",
    "snow",
    "soft",
    "warm",
    "wind"
  ],
  "path_html": "data/2023/12/05/haiku.2023-12-05.05.html",
  "path_json": "data/2023/12/05/haiku.2023-12-05.05.json",
  "created": "2025-12-26T03:57:46.366821+00:00"
}