{
  "id": "20220113-02",
  "date": "2022-01-13",
  "seq": 2,
  "title": "2022-01-13.02",
  "lines": [
    "all I want to see",
    "people embracing changes",
    "celebrating life"
  ],
  "tags": [
    "all",
    "celebrating",
    "changes",
    "embracing",
    "i",
    "life",
    "people",
    "see",
    "to",
    "want"
  ],
  "path_html": "data/2022/01/13/haiku.2022-01-13.02.html",
  "path_json": "data/2022/01/13/haiku.2022-01-13.02.json",
  "created": "2025-09-29T08:35:11.582784+00:00"
}