{
  "id": "20220502-01",
  "date": "2022-05-02",
  "seq": 1,
  "title": "2022-05-02.01",
  "lines": [
    "holidays scamper",
    "within laughter lit hallways",
    "joyful yet too brief"
  ],
  "tags": [
    "brief",
    "hallways",
    "holidays",
    "joyful",
    "laughter",
    "lit",
    "scamper",
    "too",
    "within",
    "yet"
  ],
  "path_html": "data/2022/05/02/haiku.2022-05-02.01.html",
  "path_json": "data/2022/05/02/haiku.2022-05-02.01.json",
  "created": "2025-09-29T08:35:12.574271+00:00"
}