{
  "id": "20210820-02",
  "date": "2021-08-20",
  "seq": 2,
  "title": "2021-08-20.02",
  "lines": [
    "move the rock aside",
    "just as stones were cast away",
    "by asking questions"
  ],
  "tags": [
    "as",
    "aside",
    "asking",
    "away",
    "by",
    "cast",
    "just",
    "move",
    "questions",
    "rock",
    "stones",
    "were"
  ],
  "path_html": "data/2021/08/20/haiku.2021-08-20.02.html",
  "path_json": "data/2021/08/20/haiku.2021-08-20.02.json",
  "created": "2025-09-29T08:35:10.223822+00:00"
}