{
  "id": "20210413-05",
  "date": "2021-04-13",
  "seq": 5,
  "title": "2021-04-13.05",
  "lines": [
    "the ancient trees sway",
    "with knowledge of the wood green",
    "wild and powerful"
  ],
  "tags": [
    "ancient",
    "and",
    "green",
    "knowledge",
    "of",
    "powerful",
    "sway",
    "trees",
    "wild",
    "with",
    "wood"
  ],
  "path_html": "data/2021/04/13/haiku.2021-04-13.05.html",
  "path_json": "data/2021/04/13/haiku.2021-04-13.05.json",
  "created": "2025-09-29T08:35:09.156299+00:00"
}