{
  "id": "20220214-04",
  "date": "2022-02-14",
  "seq": 4,
  "title": "2022-02-14.04",
  "lines": [
    "testing the waters",
    "ripples spreading from first steps",
    "calming the ocean"
  ],
  "tags": [
    "calming",
    "first",
    "from",
    "ocean",
    "ripples",
    "spreading",
    "steps",
    "testing",
    "waters"
  ],
  "path_html": "data/2022/02/14/haiku.2022-02-14.04.html",
  "path_json": "data/2022/02/14/haiku.2022-02-14.04.json",
  "created": "2025-09-29T08:35:11.872256+00:00"
}