{
  "id": "20220322-04",
  "date": "2022-03-22",
  "seq": 4,
  "title": "2022-03-22.04",
  "lines": [
    "within these moments",
    "are all the time of the world",
    "running down your cheek"
  ],
  "tags": [
    "all",
    "are",
    "cheek",
    "down",
    "moments",
    "of",
    "running",
    "time",
    "within",
    "world",
    "your"
  ],
  "path_html": "data/2022/03/22/haiku.2022-03-22.04.html",
  "path_json": "data/2022/03/22/haiku.2022-03-22.04.json",
  "created": "2025-09-29T08:35:12.197022+00:00"
}