{
  "id": "20241013-01",
  "date": "2024-10-13",
  "seq": 1,
  "title": "2024-10-13.01",
  "lines": [
    "summer breathes softly",
    "spiders shadows drift through birth",
    "time pauses, listening"
  ],
  "tags": [
    "birth",
    "breathes",
    "drift",
    "pauses",
    "shadows",
    "spiders",
    "summer",
    "time"
  ],
  "path_html": "data/2024/10/13/haiku.2024-10-13.01.html",
  "path_json": "data/2024/10/13/haiku.2024-10-13.01.json",
  "created": "2025-12-26T04:21:59.286212+00:00"
}