{
  "id": "20220110-02",
  "date": "2022-01-10",
  "seq": 2,
  "title": "2022-01-10.02",
  "lines": [
    "trusting the shallows",
    "where life and beauty lurking",
    "seek to impress us"
  ],
  "tags": [
    "and",
    "beauty",
    "impress",
    "life",
    "lurking",
    "seek",
    "shallows",
    "to",
    "trusting",
    "us",
    "where"
  ],
  "path_html": "data/2022/01/10/haiku.2022-01-10.02.html",
  "path_json": "data/2022/01/10/haiku.2022-01-10.02.json",
  "created": "2025-09-29T08:35:11.555909+00:00"
}