{
  "id": "20210913-04",
  "date": "2021-09-13",
  "seq": 4,
  "title": "2021-09-13.04",
  "lines": [
    "we move through the sea",
    "swimming and gliding with ease",
    "marveling at life"
  ],
  "tags": [
    "and",
    "at",
    "ease",
    "gliding",
    "life",
    "marveling",
    "move",
    "sea",
    "swimming",
    "through",
    "with"
  ],
  "path_html": "data/2021/09/13/haiku.2021-09-13.04.html",
  "path_json": "data/2021/09/13/haiku.2021-09-13.04.json",
  "created": "2025-09-29T08:35:10.438655+00:00"
}