{
  "id": "20220125-04",
  "date": "2022-01-25",
  "seq": 4,
  "title": "2022-01-25.04",
  "lines": [
    "gliding through grey mists",
    "running over tracks and hills",
    "carrying us all"
  ],
  "tags": [
    "all",
    "and",
    "carrying",
    "gliding",
    "grey",
    "hills",
    "mists",
    "over",
    "running",
    "through",
    "tracks",
    "us"
  ],
  "path_html": "data/2022/01/25/haiku.2022-01-25.04.html",
  "path_json": "data/2022/01/25/haiku.2022-01-25.04.json",
  "created": "2025-09-29T08:35:11.693014+00:00"
}