{
  "id": "20210719-02",
  "date": "2021-07-19",
  "seq": 2,
  "title": "2021-07-19.02",
  "lines": [
    "no matter where then.",
    "we grow where we are planted",
    "and we strive and thrive"
  ],
  "tags": [
    "and",
    "are",
    "grow",
    "matter",
    "no",
    "planted",
    "strive",
    "then",
    "thrive",
    "where"
  ],
  "path_html": "data/2021/07/19/haiku.2021-07-19.02.html",
  "path_json": "data/2021/07/19/haiku.2021-07-19.02.json",
  "created": "2025-09-29T08:35:09.952097+00:00"
}