{
  "id": "20211107-02",
  "date": "2021-11-07",
  "seq": 2,
  "title": "2021-11-07.02",
  "lines": [
    "sipping cool water",
    "trickles down the grateful throat",
    "simple remedies"
  ],
  "tags": [
    "cool",
    "down",
    "grateful",
    "remedies",
    "simple",
    "sipping",
    "throat",
    "trickles",
    "water"
  ],
  "path_html": "data/2021/11/07/haiku.2021-11-07.02.html",
  "path_json": "data/2021/11/07/haiku.2021-11-07.02.json",
  "created": "2025-09-29T08:35:10.983396+00:00"
}