{
  "id": "20211107-05",
  "date": "2021-11-07",
  "seq": 5,
  "title": "2021-11-07.05",
  "lines": [
    "twenty days and nights",
    "walking alone and yet no",
    "within the desert"
  ],
  "tags": [
    "alone",
    "and",
    "days",
    "desert",
    "nights",
    "no",
    "twenty",
    "walking",
    "within",
    "yet"
  ],
  "path_html": "data/2021/11/07/haiku.2021-11-07.05.html",
  "path_json": "data/2021/11/07/haiku.2021-11-07.05.json",
  "created": "2025-09-29T08:35:10.988751+00:00"
}