{
  "id": "20210528-02",
  "date": "2021-05-28",
  "seq": 2,
  "title": "2021-05-28.02",
  "lines": [
    "build an ark and live",
    "strong advice for ancient times",
    "good advice for now"
  ],
  "tags": [
    "advice",
    "ancient",
    "and",
    "ark",
    "build",
    "for",
    "good",
    "live",
    "now",
    "strong",
    "times"
  ],
  "path_html": "data/2021/05/28/haiku.2021-05-28.02.html",
  "path_json": "data/2021/05/28/haiku.2021-05-28.02.json",
  "created": "2025-09-29T08:35:09.525243+00:00"
}