{
  "id": "20210217-03",
  "date": "2021-02-17",
  "seq": 3,
  "title": "2021-02-17.03",
  "lines": [
    "goldilocks moments",
    "shelter the earth from ruin",
    "smallest of degrees"
  ],
  "tags": [
    "degrees",
    "earth",
    "from",
    "goldilocks",
    "moments",
    "of",
    "ruin",
    "shelter",
    "smallest"
  ],
  "path_html": "data/2021/02/17/haiku.2021-02-17.03.html",
  "path_json": "data/2021/02/17/haiku.2021-02-17.03.json",
  "created": "2025-09-29T08:35:08.743354+00:00"
}