{
  "id": "20170919-03",
  "date": "2017-09-19",
  "seq": 3,
  "title": "2017-09-19.03",
  "lines": [
    "summer breathes softly",
    "rivers shadows drift through moon",
    "time pauses, listening"
  ],
  "tags": [
    "breathes",
    "drift",
    "moon",
    "pauses",
    "rivers",
    "shadows",
    "summer",
    "time"
  ],
  "path_html": "data/2017/09/19/haiku.2017-09-19.03.html",
  "path_json": "data/2017/09/19/haiku.2017-09-19.03.json",
  "created": "2025-12-25T06:30:08.026385+00:00"
}