{
  "id": "20220116-04",
  "date": "2022-01-16",
  "seq": 4,
  "title": "2022-01-16.04",
  "lines": [
    "choices are crossroads",
    "decisions propel onwards",
    "preparing for more"
  ],
  "tags": [
    "are",
    "choices",
    "crossroads",
    "decisions",
    "for",
    "more",
    "onwards",
    "preparing",
    "propel"
  ],
  "path_html": "data/2022/01/16/haiku.2022-01-16.04.html",
  "path_json": "data/2022/01/16/haiku.2022-01-16.04.json",
  "created": "2025-09-29T08:35:11.609896+00:00"
}