{
  "id": "20211211-05",
  "date": "2021-12-11",
  "seq": 5,
  "title": "2021-12-11.05",
  "lines": [
    "and now we are three",
    "soon then to be thirty-three",
    "watching with wonder"
  ],
  "tags": [
    "and",
    "are",
    "be",
    "now",
    "soon",
    "then",
    "thirty",
    "three",
    "to",
    "watching",
    "with",
    "wonder"
  ],
  "path_html": "data/2021/12/11/haiku.2021-12-11.05.html",
  "path_json": "data/2021/12/11/haiku.2021-12-11.05.json",
  "created": "2025-09-29T08:35:11.291570+00:00"
}