{
  "id": "20210823-01",
  "date": "2021-08-23",
  "seq": 1,
  "title": "2021-08-23.01",
  "lines": [
    "breaking secrets down",
    "flushing out the false faces",
    "building new belief"
  ],
  "tags": [
    "belief",
    "breaking",
    "building",
    "down",
    "faces",
    "false",
    "flushing",
    "new",
    "out",
    "secrets"
  ],
  "path_html": "data/2021/08/23/haiku.2021-08-23.01.html",
  "path_json": "data/2021/08/23/haiku.2021-08-23.01.json",
  "created": "2025-09-29T08:35:10.247012+00:00"
}