{
  "id": "20220406-02",
  "date": "2022-04-06",
  "seq": 2,
  "title": "2022-04-06.02",
  "lines": [
    "white feathers blessing",
    "spread within churches and homes",
    "a sign from heaven"
  ],
  "tags": [
    "and",
    "blessing",
    "churches",
    "feathers",
    "from",
    "heaven",
    "homes",
    "sign",
    "spread",
    "white",
    "within"
  ],
  "path_html": "data/2022/04/06/haiku.2022-04-06.02.html",
  "path_json": "data/2022/04/06/haiku.2022-04-06.02.json",
  "created": "2025-09-29T08:35:12.341994+00:00"
}