{
  "id": "20230327-03",
  "date": "2023-03-27",
  "seq": 3,
  "title": "2023-03-27.03",
  "lines": [
    "summer breathes softly",
    "windows shadows drift through moon",
    "time pauses, listening"
  ],
  "tags": [
    "breathes",
    "drift",
    "moon",
    "pauses",
    "shadows",
    "summer",
    "time",
    "windows"
  ],
  "path_html": "data/2023/03/27/haiku.2023-03-27.03.html",
  "path_json": "data/2023/03/27/haiku.2023-03-27.03.json",
  "created": "2025-12-26T03:57:46.676423+00:00"
}