{
  "id": "20230604-02",
  "date": "2023-06-04",
  "seq": 2,
  "title": "2023-06-04.02",
  "lines": [
    "Warm air moves softly",
    "Wind moves across open fields",
    "Heat starts to drift off"
  ],
  "tags": [
    "air",
    "drift",
    "fields",
    "heat",
    "moves",
    "open",
    "starts",
    "warm",
    "wind"
  ],
  "path_html": "data/2023/06/04/haiku.2023-06-04.02.html",
  "path_json": "data/2023/06/04/haiku.2023-06-04.02.json",
  "created": "2025-12-26T03:57:44.182524+00:00"
}