{
  "id": "20220424-03",
  "date": "2022-04-24",
  "seq": 3,
  "title": "2022-04-24.03",
  "lines": [
    "simple letters show",
    "steps in reason paths in faith",
    "within the same book"
  ],
  "tags": [
    "book",
    "faith",
    "in",
    "letters",
    "paths",
    "reason",
    "same",
    "show",
    "simple",
    "steps",
    "within"
  ],
  "path_html": "data/2022/04/24/haiku.2022-04-24.03.html",
  "path_json": "data/2022/04/24/haiku.2022-04-24.03.json",
  "created": "2025-09-29T08:35:12.502810+00:00"
}