{
  "id": "20210514-04",
  "date": "2021-05-14",
  "seq": 4,
  "title": "2021-05-14.04",
  "lines": [
    "dawn moving forward",
    "dismantling dusky haze",
    "pouring through the fog"
  ],
  "tags": [
    "dawn",
    "dismantling",
    "dusky",
    "fog",
    "forward",
    "haze",
    "moving",
    "pouring",
    "through"
  ],
  "path_html": "data/2021/05/14/haiku.2021-05-14.04.html",
  "path_json": "data/2021/05/14/haiku.2021-05-14.04.json",
  "created": "2025-09-29T08:35:09.394118+00:00"
}