{
  "id": "20210514-02",
  "date": "2021-05-14",
  "seq": 2,
  "title": "2021-05-14.02",
  "lines": [
    "bass scuttles around",
    "building up to the bass kick",
    "who fears one three eight?"
  ],
  "tags": [
    "around",
    "bass",
    "building",
    "eight",
    "fears",
    "kick",
    "one",
    "scuttles",
    "three",
    "to",
    "up",
    "who"
  ],
  "path_html": "data/2021/05/14/haiku.2021-05-14.02.html",
  "path_json": "data/2021/05/14/haiku.2021-05-14.02.json",
  "created": "2025-09-29T08:35:09.391622+00:00"
}