{
  "id": "20251226-2519",
  "date": "2025-12-26",
  "seq": 2519,
  "title": "2025-12-26.2519",
  "lines": [
    "summer breathes softly",
    "trees shadows drift through sun",
    "time pauses, listening"
  ],
  "tags": [
    "breathes",
    "drift",
    "pauses",
    "shadows",
    "summer",
    "sun",
    "time",
    "trees"
  ],
  "path_html": "data/2025/12/26/haiku.2025-12-26.2519.html",
  "path_json": "data/2025/12/26/haiku.2025-12-26.2519.json",
  "created": "2025-12-26T03:57:45.649119+00:00"
}