{
  "id": "20251226-751",
  "date": "2025-12-26",
  "seq": 751,
  "title": "2025-12-26.751",
  "lines": [
    "Children laugh at dusk",
    "Waves comb the shore, then retreat",
    "Plans gently fade now"
  ],
  "tags": [
    "children",
    "comb",
    "dusk",
    "fade",
    "laugh",
    "plans",
    "retreat",
    "shore",
    "waves"
  ],
  "path_html": "data/2025/12/26/haiku.2025-12-26.751.html",
  "path_json": "data/2025/12/26/haiku.2025-12-26.751.json",
  "created": "2025-12-26T03:57:44.709339+00:00"
}