{
  "id": "20251226-492",
  "date": "2025-12-26",
  "seq": 492,
  "title": "2025-12-26.492",
  "lines": [
    "breathes summer softly",
    "morning shadows drift through sun",
    "time pauses, listening"
  ],
  "tags": [
    "breathes",
    "drift",
    "morning",
    "pauses",
    "shadows",
    "summer",
    "sun",
    "time"
  ],
  "path_html": "data/2025/12/26/haiku.2025-12-26.492.html",
  "path_json": "data/2025/12/26/haiku.2025-12-26.492.json",
  "created": "2025-12-26T04:21:58.895248+00:00"
}