{
  "id": "20251226-1176",
  "date": "2025-12-26",
  "seq": 1176,
  "title": "2025-12-26.1176",
  "lines": [
    "summer breathes softly",
    "rivers shadows through drift jinja",
    "time pauses, listening"
  ],
  "tags": [
    "breathes",
    "drift",
    "jinja",
    "pauses",
    "rivers",
    "shadows",
    "summer",
    "time"
  ],
  "path_html": "data/2025/12/26/haiku.2025-12-26.1176.html",
  "path_json": "data/2025/12/26/haiku.2025-12-26.1176.json",
  "created": "2025-12-26T03:57:44.929857+00:00"
}