{
  "id": "20251226-2615",
  "date": "2025-12-26",
  "seq": 2615,
  "title": "2025-12-26.2615",
  "lines": [
    "slow wind quiet cold faint",
    "wanders holds circles ridge shore",
    "silence opens breaks"
  ],
  "tags": [
    "breaks",
    "circles",
    "cold",
    "faint",
    "opens",
    "quiet",
    "ridge",
    "shore",
    "silence",
    "wanders",
    "wind"
  ],
  "path_html": "data/2025/12/26/haiku.2025-12-26.2615.html",
  "path_json": "data/2025/12/26/haiku.2025-12-26.2615.json",
  "created": "2025-12-26T03:57:45.699590+00:00"
}