{
  "id": "20251226-1592",
  "date": "2025-12-26",
  "seq": 1592,
  "title": "2025-12-26.1592",
  "lines": [
    "Frozen river bends",
    "Prayer moves through frozen air",
    "Silence answers back"
  ],
  "tags": [
    "air",
    "answers",
    "bends",
    "frozen",
    "moves",
    "prayer",
    "river",
    "silence"
  ],
  "path_html": "data/2025/12/26/haiku.2025-12-26.1592.html",
  "path_json": "data/2025/12/26/haiku.2025-12-26.1592.json",
  "created": "2025-12-26T03:57:45.158817+00:00"
}