{
  "id": "20251226-871",
  "date": "2025-12-26",
  "seq": 871,
  "title": "2025-12-26.871",
  "lines": [
    "Morning crowd arrives,",
    "coffee warms the restless hands,",
    "trains move into day."
  ],
  "tags": [
    "arrives",
    "coffee",
    "crowd",
    "day",
    "hands",
    "morning",
    "move",
    "restless",
    "trains",
    "warms"
  ],
  "path_html": "data/2025/12/26/haiku.2025-12-26.871.html",
  "path_json": "data/2025/12/26/haiku.2025-12-26.871.json",
  "created": "2025-12-26T03:57:44.771005+00:00"
}