{
  "id": "20251226-1471",
  "date": "2025-12-26",
  "seq": 1471,
  "title": "2025-12-26.1471",
  "lines": [
    "Green fields drink the rain",
    "Mist drifts along quiet roads",
    "Day slips into rest"
  ],
  "tags": [
    "day",
    "drifts",
    "drink",
    "fields",
    "green",
    "mist",
    "quiet",
    "rain",
    "rest",
    "roads",
    "slips"
  ],
  "path_html": "data/2025/12/26/haiku.2025-12-26.1471.html",
  "path_json": "data/2025/12/26/haiku.2025-12-26.1471.json",
  "created": "2025-12-26T03:57:45.095991+00:00"
}