{
  "id": "20251226-2405",
  "date": "2025-12-26",
  "seq": 2405,
  "title": "2025-12-26.2405",
  "lines": [
    "summer breathes softly",
    "oceans shadows drift through trees",
    "time pauses, listening"
  ],
  "tags": [
    "breathes",
    "drift",
    "oceans",
    "pauses",
    "shadows",
    "summer",
    "time",
    "trees"
  ],
  "path_html": "data/2025/12/26/haiku.2025-12-26.2405.html",
  "path_json": "data/2025/12/26/haiku.2025-12-26.2405.json",
  "created": "2025-12-26T03:57:45.589224+00:00"
}