{
  "id": "20251226-1829",
  "date": "2025-12-26",
  "seq": 1829,
  "title": "2025-12-26.1829",
  "lines": [
    "water wind signal",
    "heavy wave lantern ridge shore",
    "lantern leaf soft path"
  ],
  "tags": [
    "heavy",
    "lantern",
    "leaf",
    "path",
    "ridge",
    "shore",
    "signal",
    "soft",
    "water",
    "wave",
    "wind"
  ],
  "path_html": "data/2025/12/26/haiku.2025-12-26.1829.html",
  "path_json": "data/2025/12/26/haiku.2025-12-26.1829.json",
  "created": "2025-12-26T03:57:45.284434+00:00"
}