{
  "id": "20251226-390",
  "date": "2025-12-26",
  "seq": 390,
  "title": "2025-12-26.390",
  "lines": [
    "quiet footprint water",
    "silence breaks drifts silence holds",
    "empty ember leaf"
  ],
  "tags": [
    "breaks",
    "drifts",
    "ember",
    "empty",
    "footprint",
    "leaf",
    "quiet",
    "silence",
    "water"
  ],
  "path_html": "data/2025/12/26/haiku.2025-12-26.390.html",
  "path_json": "data/2025/12/26/haiku.2025-12-26.390.json",
  "created": "2025-12-26T03:26:41.478821+00:00"
}