{
  "id": "20251226-744",
  "date": "2025-12-26",
  "seq": 744,
  "title": "2025-12-26.744",
  "lines": [
    "summer breathes softly",
    "winter shadows drift through beach",
    "time pauses, listening"
  ],
  "tags": [
    "beach",
    "breathes",
    "drift",
    "pauses",
    "shadows",
    "summer",
    "time",
    "winter"
  ],
  "path_html": "data/2025/12/26/haiku.2025-12-26.744.html",
  "path_json": "data/2025/12/26/haiku.2025-12-26.744.json",
  "created": "2025-12-26T03:26:41.682159+00:00"
}