{
  "id": "20251226-2015",
  "date": "2025-12-26",
  "seq": 2015,
  "title": "2025-12-26.2015",
  "lines": [
    "summer breathes softly",
    "trees shadows drift through moon",
    "time pauses, listening"
  ],
  "tags": [
    "breathes",
    "drift",
    "moon",
    "pauses",
    "shadows",
    "summer",
    "time",
    "trees"
  ],
  "path_html": "data/2025/12/26/haiku.2025-12-26.2015.html",
  "path_json": "data/2025/12/26/haiku.2025-12-26.2015.json",
  "created": "2025-12-26T03:57:45.380927+00:00"
}