{
  "id": "20251226-2767",
  "date": "2025-12-26",
  "seq": 2767,
  "title": "2025-12-26.2767",
  "lines": [
    "Forest breathes in mist",
    "Tengu glide on mountain air",
    "Day waits its turn now"
  ],
  "tags": [
    "air",
    "breathes",
    "day",
    "forest",
    "glide",
    "mist",
    "mountain",
    "tengu",
    "turn",
    "waits"
  ],
  "path_html": "data/2025/12/26/haiku.2025-12-26.2767.html",
  "path_json": "data/2025/12/26/haiku.2025-12-26.2767.json",
  "created": "2025-12-26T03:57:45.779018+00:00"
}