{
  "id": "20251226-46",
  "date": "2025-12-26",
  "seq": 46,
  "title": "2025-12-26.46",
  "lines": [
    "summer breathes softly",
    "spiders shadows drift through fingerprints",
    "time pauses, listening"
  ],
  "tags": [
    "breathes",
    "drift",
    "fingerprints",
    "pauses",
    "shadows",
    "spiders",
    "summer",
    "time"
  ],
  "path_html": "data/2025/12/26/haiku.2025-12-26.46.html",
  "path_json": "data/2025/12/26/haiku.2025-12-26.46.json",
  "created": "2025-12-26T03:26:41.300731+00:00"
}