{
  "id": "20251226-1226",
  "date": "2025-12-26",
  "seq": 1226,
  "title": "2025-12-26.1226",
  "lines": [
    "Cloud shadows pass by",
    "Fog drifts across the valley",
    "The heat loosens grip"
  ],
  "tags": [
    "cloud",
    "drifts",
    "fog",
    "grip",
    "heat",
    "loosens",
    "pass",
    "shadows",
    "valley"
  ],
  "path_html": "data/2025/12/26/haiku.2025-12-26.1226.html",
  "path_json": "data/2025/12/26/haiku.2025-12-26.1226.json",
  "created": "2025-12-26T03:57:44.955929+00:00"
}