{
  "id": "20251226-2785",
  "date": "2025-12-26",
  "seq": 2785,
  "title": "2025-12-26.2785",
  "lines": [
    "summer breathes softly",
    "spring shadows drift through morning",
    "time pauses, listening"
  ],
  "tags": [
    "breathes",
    "drift",
    "morning",
    "pauses",
    "shadows",
    "spring",
    "summer",
    "time"
  ],
  "path_html": "data/2025/12/26/haiku.2025-12-26.2785.html",
  "path_json": "data/2025/12/26/haiku.2025-12-26.2785.json",
  "created": "2025-12-26T03:57:45.789648+00:00"
}