{
  "id": "20251226-2581",
  "date": "2025-12-26",
  "seq": 2581,
  "title": "2025-12-26.2581",
  "lines": [
    "settles shadow stone",
    "leaf echo slow snow glass wave",
    "stone warm path deer dim"
  ],
  "tags": [
    "deer",
    "dim",
    "echo",
    "glass",
    "leaf",
    "path",
    "settles",
    "shadow",
    "snow",
    "stone",
    "warm",
    "wave"
  ],
  "path_html": "data/2025/12/26/haiku.2025-12-26.2581.html",
  "path_json": "data/2025/12/26/haiku.2025-12-26.2581.json",
  "created": "2025-12-26T03:57:45.681790+00:00"
}