{
  "id": "20251226-1004",
  "date": "2025-12-26",
  "seq": 1004,
  "title": "2025-12-26.1004",
  "lines": [
    "Green fields drink the rain",
    "Wind moves across open fields",
    "The heat loosens grip"
  ],
  "tags": [
    "drink",
    "fields",
    "green",
    "grip",
    "heat",
    "loosens",
    "moves",
    "open",
    "rain",
    "wind"
  ],
  "path_html": "data/2025/12/26/haiku.2025-12-26.1004.html",
  "path_json": "data/2025/12/26/haiku.2025-12-26.1004.json",
  "created": "2025-12-26T04:21:59.151908+00:00"
}