{
  "id": "20251226-2072",
  "date": "2025-12-26",
  "seq": 2072,
  "title": "2025-12-26.2072",
  "lines": [
    "fireplace lingers",
    "quiet breath in borrowed light",
    "sleep turns the page"
  ],
  "tags": [
    "breath",
    "fireplace",
    "light",
    "lingers",
    "page",
    "quiet",
    "sleep",
    "turns"
  ],
  "path_html": "data/2025/12/26/haiku.2025-12-26.2072.html",
  "path_json": "data/2025/12/26/haiku.2025-12-26.2072.json",
  "created": "2025-12-26T03:57:45.411018+00:00"
}