{
  "id": "20210228-01",
  "date": "2021-02-28",
  "seq": 1,
  "title": "2021-02-28.01",
  "lines": [
    "small feet unsteady",
    "stumbling, walking, then running",
    "as the years move by"
  ],
  "tags": [
    "as",
    "by",
    "feet",
    "move",
    "running",
    "small",
    "stumbling",
    "then",
    "unsteady",
    "walking",
    "years"
  ],
  "path_html": "data/2021/02/28/haiku.2021-02-28.01.html",
  "path_json": "data/2021/02/28/haiku.2021-02-28.01.json",
  "created": "2025-09-29T08:35:08.827054+00:00"
}