{
  "id": "20190422-03",
  "date": "2019-04-22",
  "seq": 3,
  "title": "2019-04-22.03",
  "lines": [
    "Warm air moves softly",
    "Fog slithers between dim trees",
    "Heat starts to drift off"
  ],
  "tags": [
    "air",
    "dim",
    "drift",
    "fog",
    "heat",
    "moves",
    "slithers",
    "starts",
    "trees",
    "warm"
  ],
  "path_html": "data/2019/04/22/haiku.2019-04-22.03.html",
  "path_json": "data/2019/04/22/haiku.2019-04-22.03.json",
  "created": "2025-12-26T03:26:42.207387+00:00"
}