{
  "id": "20210903-02",
  "date": "2021-09-03",
  "seq": 2,
  "title": "2021-09-03.02",
  "lines": [
    "step into the waves",
    "as the seventh crashes down",
    "washing away fear"
  ],
  "tags": [
    "as",
    "away",
    "crashes",
    "down",
    "fear",
    "into",
    "seventh",
    "step",
    "washing",
    "waves"
  ],
  "path_html": "data/2021/09/03/haiku.2021-09-03.02.html",
  "path_json": "data/2021/09/03/haiku.2021-09-03.02.json",
  "created": "2025-09-29T08:35:10.344745+00:00"
}