{
  "id": "20210829-01",
  "date": "2021-08-29",
  "seq": 1,
  "title": "2021-08-29.01",
  "lines": [
    "Puzzling through it",
    "we see the outline of life",
    "and see how things were"
  ],
  "tags": [
    "and",
    "how",
    "it",
    "life",
    "of",
    "outline",
    "puzzling",
    "see",
    "things",
    "through",
    "were"
  ],
  "path_html": "data/2021/08/29/haiku.2021-08-29.01.html",
  "path_json": "data/2021/08/29/haiku.2021-08-29.01.json",
  "created": "2025-09-29T08:35:10.299446+00:00"
}