{
  "id": "20220510-01",
  "date": "2022-05-10",
  "seq": 1,
  "title": "2022-05-10.01",
  "lines": [
    "along the river",
    "turtles and herons bathing",
    "green, white, and blue lines"
  ],
  "tags": [
    "along",
    "and",
    "bathing",
    "blue",
    "green",
    "herons",
    "lines",
    "river",
    "turtles",
    "white"
  ],
  "path_html": "data/2022/05/10/haiku.2022-05-10.01.html",
  "path_json": "data/2022/05/10/haiku.2022-05-10.01.json",
  "created": "2025-09-29T08:35:12.641477+00:00"
}