{
  "id": "20251225-429",
  "date": "2025-12-25",
  "seq": 429,
  "title": "2025-12-25.429",
  "lines": [
    "ridge forests early",
    "wanders leans cold warm empty",
    "fades opens bare"
  ],
  "tags": [
    "bare",
    "cold",
    "empty",
    "fades",
    "forests",
    "leans",
    "opens",
    "ridge",
    "wanders",
    "warm"
  ],
  "path_html": "data/2025/12/25/haiku.2025-12-25.429.html",
  "path_json": "data/2025/12/25/haiku.2025-12-25.429.json",
  "created": "2025-12-25T06:30:07.353271+00:00"
}