{
  "id": "20251225-694",
  "date": "2025-12-25",
  "seq": 694,
  "title": "2025-12-25.694",
  "lines": [
    "summer breathes softly",
    "fall shadows drift through fingerprints",
    "time pauses, listening"
  ],
  "tags": [
    "breathes",
    "drift",
    "fall",
    "fingerprints",
    "pauses",
    "shadows",
    "summer",
    "time"
  ],
  "path_html": "data/2025/12/25/haiku.2025-12-25.694.html",
  "path_json": "data/2025/12/25/haiku.2025-12-25.694.json",
  "created": "2025-12-25T06:30:07.491470+00:00"
}