{
  "id": "20251225-884",
  "date": "2025-12-25",
  "seq": 884,
  "title": "2025-12-25.884",
  "lines": [
    "summer breathes softly",
    "beach shadows drift through rabbits",
    "time pauses, listening"
  ],
  "tags": [
    "beach",
    "breathes",
    "drift",
    "pauses",
    "rabbits",
    "shadows",
    "summer",
    "time"
  ],
  "path_html": "data/2025/12/25/haiku.2025-12-25.884.html",
  "path_json": "data/2025/12/25/haiku.2025-12-25.884.json",
  "created": "2025-12-25T06:30:07.587455+00:00"
}