{
  "id": "20251225-857",
  "date": "2025-12-25",
  "seq": 857,
  "title": "2025-12-25.857",
  "lines": [
    "summer breathes softly",
    "trees shadows drift through new years",
    "time pauses, listening"
  ],
  "tags": [
    "breathes",
    "drift",
    "new",
    "pauses",
    "shadows",
    "summer",
    "time",
    "trees",
    "years"
  ],
  "path_html": "data/2025/12/25/haiku.2025-12-25.857.html",
  "path_json": "data/2025/12/25/haiku.2025-12-25.857.json",
  "created": "2025-12-25T06:30:07.573910+00:00"
}