{
  "id": "20251225-635",
  "date": "2025-12-25",
  "seq": 635,
  "title": "2025-12-25.635",
  "lines": [
    "summer breathes softly",
    "spring shadows drift through trees",
    "time pauses, listening"
  ],
  "tags": [
    "breathes",
    "drift",
    "pauses",
    "shadows",
    "spring",
    "summer",
    "time",
    "trees"
  ],
  "path_html": "data/2025/12/25/haiku.2025-12-25.635.html",
  "path_json": "data/2025/12/25/haiku.2025-12-25.635.json",
  "created": "2025-12-25T06:30:07.461949+00:00"
}