{
  "id": "20251225-387",
  "date": "2025-12-25",
  "seq": 387,
  "title": "2025-12-25.387",
  "lines": [
    "water shore ember",
    "warm footprint opens pale slips",
    "ridge wave glass opens"
  ],
  "tags": [
    "ember",
    "footprint",
    "glass",
    "opens",
    "pale",
    "ridge",
    "shore",
    "slips",
    "warm",
    "water",
    "wave"
  ],
  "path_html": "data/2025/12/25/haiku.2025-12-25.387.html",
  "path_json": "data/2025/12/25/haiku.2025-12-25.387.json",
  "created": "2025-12-25T06:30:07.330381+00:00"
}