{
  "id": "20251225-1023",
  "date": "2025-12-25",
  "seq": 1023,
  "title": "2025-12-25.1023",
  "lines": [
    "summer breathes softly",
    "morning shadows drift through midnight",
    "time pauses, listening"
  ],
  "tags": [
    "breathes",
    "drift",
    "midnight",
    "morning",
    "pauses",
    "shadows",
    "summer",
    "time"
  ],
  "path_html": "data/2025/12/25/haiku.2025-12-25.1023.html",
  "path_json": "data/2025/12/25/haiku.2025-12-25.1023.json",
  "created": "2025-12-25T06:30:07.657368+00:00"
}