{
  "id": "20251225-868",
  "date": "2025-12-25",
  "seq": 868,
  "title": "2025-12-25.868",
  "lines": [
    "summer breathes softly",
    "beach shadows drift through afternoon",
    "time pauses, listening"
  ],
  "tags": [
    "afternoon",
    "beach",
    "breathes",
    "drift",
    "pauses",
    "shadows",
    "summer",
    "time"
  ],
  "path_html": "data/2025/12/25/haiku.2025-12-25.868.html",
  "path_json": "data/2025/12/25/haiku.2025-12-25.868.json",
  "created": "2025-12-25T06:30:07.579373+00:00"
}