{
  "id": "20251225-1292",
  "date": "2025-12-25",
  "seq": 1292,
  "title": "2025-12-25.1292",
  "lines": [
    "forests and footsteps",
    "two currents cross in stillness",
    "time listens, unmoved"
  ],
  "tags": [
    "cross",
    "currents",
    "footsteps",
    "forests",
    "listens",
    "stillness",
    "time",
    "unmoved"
  ],
  "path_html": "data/2025/12/25/haiku.2025-12-25.1292.html",
  "path_json": "data/2025/12/25/haiku.2025-12-25.1292.json",
  "created": "2025-12-25T06:30:07.791919+00:00"
}