{
  "id": "20251225-1002",
  "date": "2025-12-25",
  "seq": 1002,
  "title": "2025-12-25.1002",
  "lines": [
    "summer breathes softly",
    "dawn shadows drift through spiders",
    "time pauses, listening"
  ],
  "tags": [
    "breathes",
    "dawn",
    "drift",
    "pauses",
    "shadows",
    "spiders",
    "summer",
    "time"
  ],
  "path_html": "data/2025/12/25/haiku.2025-12-25.1002.html",
  "path_json": "data/2025/12/25/haiku.2025-12-25.1002.json",
  "created": "2025-12-25T06:30:07.646737+00:00"
}