{
  "id": "20251225-1222",
  "date": "2025-12-25",
  "seq": 1222,
  "title": "2025-12-25.1222",
  "lines": [
    "jinja (shinto temple) lingers",
    "quiet breath in borrowed light",
    "sleep turns the page"
  ],
  "tags": [
    "breath",
    "jinja",
    "light",
    "lingers",
    "page",
    "quiet",
    "shinto",
    "sleep",
    "temple",
    "turns"
  ],
  "path_html": "data/2025/12/25/haiku.2025-12-25.1222.html",
  "path_json": "data/2025/12/25/haiku.2025-12-25.1222.json",
  "created": "2025-12-25T06:30:07.756599+00:00"
}