{
  "id": "20251224-259",
  "date": "2025-12-24",
  "seq": 259,
  "title": "2025-12-24.259",
  "lines": [
    "Summer rain begins",
    "Wind moves across open fields",
    "Day slips into rest"
  ],
  "tags": [
    "begins",
    "day",
    "fields",
    "moves",
    "open",
    "rain",
    "rest",
    "slips",
    "summer",
    "wind"
  ],
  "path_html": "data/2025/12/24/haiku.2025-12-24.259.html",
  "path_json": "data/2025/12/24/haiku.2025-12-24.259.json",
  "created": "2025-12-24T07:51:51.125174+00:00"
}