{
  "id": "20251224-151",
  "date": "2025-12-24",
  "seq": 151,
  "title": "2025-12-24.151",
  "lines": [
    "Green fields drink the rain",
    "Heat presses down on the land",
    "Day slips into rest"
  ],
  "tags": [
    "day",
    "drink",
    "fields",
    "green",
    "heat",
    "land",
    "presses",
    "rain",
    "rest",
    "slips"
  ],
  "path_html": "data/2025/12/24/haiku.2025-12-24.151.html",
  "path_json": "data/2025/12/24/haiku.2025-12-24.151.json",
  "created": "2025-12-24T07:51:51.064494+00:00"
}