{
  "id": "20180114-02",
  "date": "2018-01-14",
  "seq": 2,
  "title": "2018-01-14.02",
  "lines": [
    "Cold stone by the stream",
    "Prayer moves through frozen air",
    "Silence answers back"
  ],
  "tags": [
    "air",
    "answers",
    "cold",
    "frozen",
    "moves",
    "prayer",
    "silence",
    "stone",
    "stream"
  ],
  "path_html": "data/2018/01/14/haiku.2018-01-14.02.html",
  "path_json": "data/2018/01/14/haiku.2018-01-14.02.json",
  "created": "2025-12-23T13:06:22.985298+00:00"
}