{
  "id": "20220330-01",
  "date": "2022-03-30",
  "seq": 1,
  "title": "2022-03-30.01",
  "lines": [
    "and we come back now",
    "to beginnings? or endings?",
    "either way return"
  ],
  "tags": [
    "and",
    "back",
    "beginnings",
    "come",
    "either",
    "endings",
    "now",
    "or",
    "return",
    "to",
    "way"
  ],
  "path_html": "data/2022/03/30/haiku.2022-03-30.01.html",
  "path_json": "data/2022/03/30/haiku.2022-03-30.01.json",
  "created": "2025-09-29T08:35:12.275167+00:00"
}