{
  "id": "20200102-21",
  "date": "2020-01-02",
  "seq": 21,
  "title": "2020-01-02.21",
  "lines": [
    "storm breaks in the night",
    "rain slams hard on wooden eaves",
    "heat sighs, disappears"
  ],
  "tags": [
    "breaks",
    "disappears",
    "eaves",
    "hard",
    "heat",
    "in",
    "night",
    "on",
    "rain",
    "sighs",
    "slams",
    "storm",
    "wooden"
  ],
  "path_html": "data/2020/01/02/haiku.2020-01-02.21.html",
  "path_json": "data/2020/01/02/haiku.2020-01-02.21.json",
  "created": "2025-09-29T10:06:10.729759+00:00"
}