{
  "id": "20170508-01",
  "date": "2017-05-08",
  "seq": 1,
  "title": "2017-05-08.01",
  "lines": [
    "soft bare wanders snow",
    "distant water breaks faint wind",
    "pale footprint holds night"
  ],
  "tags": [
    "bare",
    "breaks",
    "distant",
    "faint",
    "footprint",
    "night",
    "pale",
    "snow",
    "soft",
    "wanders",
    "water",
    "wind"
  ],
  "path_html": "data/2017/05/08/haiku.2017-05-08.01.html",
  "path_json": "data/2017/05/08/haiku.2017-05-08.01.json",
  "created": "2025-12-25T06:30:06.785887+00:00"
}