{
  "id": "20210611-05",
  "date": "2021-06-11",
  "seq": 5,
  "title": "2021-06-11.05",
  "lines": [
    "when the door is locked",
    "and all the lights gently dimmed",
    "peace roams grey shadows"
  ],
  "tags": [
    "all",
    "and",
    "dimmed",
    "door",
    "gently",
    "grey",
    "lights",
    "locked",
    "peace",
    "roams",
    "shadows",
    "when"
  ],
  "path_html": "data/2021/06/11/haiku.2021-06-11.05.html",
  "path_json": "data/2021/06/11/haiku.2021-06-11.05.json",
  "created": "2025-09-29T08:35:09.642150+00:00"
}