{
  "id": "20210418-03",
  "date": "2021-04-18",
  "seq": 3,
  "title": "2021-04-18.03",
  "lines": [
    "cannot say the name",
    "within the pure land sutra",
    "for what name is there?"
  ],
  "tags": [
    "cannot",
    "for",
    "land",
    "name",
    "pure",
    "say",
    "sutra",
    "there",
    "what",
    "within"
  ],
  "path_html": "data/2021/04/18/haiku.2021-04-18.03.html",
  "path_json": "data/2021/04/18/haiku.2021-04-18.03.json",
  "created": "2025-09-29T08:35:09.192769+00:00"
}