{
  "id": "20190427-02",
  "date": "2019-04-27",
  "seq": 2,
  "title": "2019-04-27.02",
  "lines": [
    "wanders holds slips wave",
    "quiet soft silence heavy pale",
    "leaf cold wanders folds"
  ],
  "tags": [
    "cold",
    "folds",
    "heavy",
    "leaf",
    "pale",
    "quiet",
    "silence",
    "slips",
    "soft",
    "wanders",
    "wave"
  ],
  "path_html": "data/2019/04/27/haiku.2019-04-27.02.html",
  "path_json": "data/2019/04/27/haiku.2019-04-27.02.json",
  "created": "2025-12-26T03:26:41.080395+00:00"
}