{
  "id": "20211118-04",
  "date": "2021-11-18",
  "seq": 4,
  "title": "2021-11-18.04",
  "lines": [
    "we can approach them",
    "standing on shores in smooth sand",
    "the sun shining high"
  ],
  "tags": [
    "approach",
    "can",
    "high",
    "in",
    "on",
    "sand",
    "shining",
    "shores",
    "smooth",
    "standing",
    "sun"
  ],
  "path_html": "data/2021/11/18/haiku.2021-11-18.04.html",
  "path_json": "data/2021/11/18/haiku.2021-11-18.04.json",
  "created": "2025-09-29T08:35:11.087593+00:00"
}