{
  "id": "20220413-02",
  "date": "2022-04-13",
  "seq": 2,
  "title": "2022-04-13.02",
  "lines": [
    "and you told me once",
    "while crying on my shoulder",
    "though that stream has dried"
  ],
  "tags": [
    "and",
    "crying",
    "dried",
    "has",
    "me",
    "my",
    "on",
    "once",
    "shoulder",
    "stream",
    "though",
    "told",
    "while"
  ],
  "path_html": "data/2022/04/13/haiku.2022-04-13.02.html",
  "path_json": "data/2022/04/13/haiku.2022-04-13.02.json",
  "created": "2025-09-29T08:35:12.405213+00:00"
}