{
  "id": "20170518-02",
  "date": "2017-05-18",
  "seq": 2,
  "title": "2017-05-18.02",
  "lines": [
    "fades circles leans",
    "cold leaf slips path birds slips leans",
    "footprint folds lantern"
  ],
  "tags": [
    "birds",
    "circles",
    "cold",
    "fades",
    "folds",
    "footprint",
    "lantern",
    "leaf",
    "leans",
    "path",
    "slips"
  ],
  "path_html": "data/2017/05/18/haiku.2017-05-18.02.html",
  "path_json": "data/2017/05/18/haiku.2017-05-18.02.json",
  "created": "2025-12-25T06:30:07.054535+00:00"
}