{
  "id": "20251223-75",
  "date": "2025-12-23",
  "seq": 75,
  "title": "2025-12-23.75",
  "lines": [
    "Spring equinox dawns",
    "Ice holds the world for a breath",
    "Lungs fill with light now"
  ],
  "tags": [
    "breath",
    "dawns",
    "equinox",
    "fill",
    "ice",
    "light",
    "lungs",
    "spring",
    "world"
  ],
  "path_html": "data/2025/12/23/haiku.2025-12-23.75.html",
  "path_json": "data/2025/12/23/haiku.2025-12-23.75.json",
  "created": "2025-12-23T11:34:38.938019+00:00"
}