{
  "id": "20251223-63",
  "date": "2025-12-23",
  "seq": 63,
  "title": "2025-12-23.63",
  "lines": [
    "Waves lean on the shore",
    "Fire sings in orange tongues",
    "Silence feels full now"
  ],
  "tags": [
    "feels",
    "fire",
    "full",
    "lean",
    "orange",
    "shore",
    "silence",
    "sings",
    "tongues",
    "waves"
  ],
  "path_html": "data/2025/12/23/haiku.2025-12-23.63.html",
  "path_json": "data/2025/12/23/haiku.2025-12-23.63.json",
  "created": "2025-12-23T11:34:38.931583+00:00"
}